README.md
docs/Makefile
docs/make.bat
docs/source/conf.py
docs/source/index.rst
docs/source/installation.rst
quilt_knit/__init__.py
quilt_knit/quilt/Connection_Interval_Tree.py
quilt_knit/quilt/Quilt.py
quilt_knit/quilt/Swatch_Neighborhood.py
quilt_knit/quilt/__init__.py
quilt_knit/swatch/Merge_Process.py
quilt_knit/swatch/Seam_Connection.py
quilt_knit/swatch/Seam_Search_Space.py
quilt_knit/swatch/Swatch.py
quilt_knit/swatch/Swatch_Connection.py
quilt_knit/swatch/Swatch_Side.py
quilt_knit/swatch/__init__.py
quilt_knit/swatch/course_boundary_instructions.py
quilt_knit/swatch/course_wise_merging/Course_Merge_Process.py
quilt_knit/swatch/course_wise_merging/Course_Seam_Connection.py
quilt_knit/swatch/course_wise_merging/Course_Seam_Search_Space.py
quilt_knit/swatch/course_wise_merging/Course_Wise_Connection.py
quilt_knit/swatch/course_wise_merging/__init__.py
quilt_knit/swatch/swatch_boundary_instruction.py
quilt_knit/swatch/wale_boundary_instructions.py
quilt_knit/swatch/wale_wise_merging/Wale_Merge_Process.py
quilt_knit/swatch/wale_wise_merging/Wale_Seam_Connection.py
quilt_knit/swatch/wale_wise_merging/Wale_Seam_Search_Space.py
quilt_knit/swatch/wale_wise_merging/Wale_Wise_Connection.py
quilt_knit/swatch/wale_wise_merging/__init__.py
quilt_knit-1.0.1.dist-info/LICENSE.md
quilt_knit-1.0.1.dist-info/METADATA
quilt_knit-1.0.1.dist-info/WHEEL
quilt_knit-1.0.1.dist-info/RECORD
