Metadata-Version: 2.1
Name: quilt-knit
Version: 1.0.1
Summary: A knit-programming library for modular combination of knitted structures defined by the knitout machine knitting language.
Home-page: https://mhofmann-khoury.github.io/QUILT/
License: License :: Free for non-commercial use
Keywords: machine knitting,act lab,Northeastern University,knitout,quilt,knit script
Author: Megan Hofmann
Author-email: m.hofmann@northeastern.edu
Maintainer: Megan Hofmann
Maintainer-email: m.hofmann@northeastern.edu
Requires-Python: >=3.11,<3.13
Classifier: Development Status :: 3 - Alpha
Classifier: Intended Audience :: Developers
Classifier: License :: Other/Proprietary License
Classifier: Natural Language :: English
Classifier: Operating System :: OS Independent
Classifier: Programming Language :: Python :: 3
Classifier: Programming Language :: Python :: 3.11
Classifier: Programming Language :: Python :: 3.12
Classifier: Topic :: Scientific/Engineering
Requires-Dist: intervaltree (>=3.1.0,<4.0.0)
Requires-Dist: knit-graphs (>=0.0.10)
Requires-Dist: knitout-interpreter (>=0.0.22)
Requires-Dist: knitout-to-dat-python (>=0.0.3)
Requires-Dist: virtual-knitting-machine (>=0.0.20)
Project-URL: Documentation, https://mhofmann-khoury.github.io/QUILT/
Project-URL: Repository, https://github.com/mhofmann-Khoury/QUILT
